torch_mpo/__init__.py
torch_mpo/decomposition/__init__.py
torch_mpo/decomposition/tt_svd.py
torch_mpo/layers/__init__.py
torch_mpo/layers/tt_conv.py
torch_mpo/layers/tt_linear.py
torch_mpo/models/__init__.py
torch_mpo/models/resnet_mpo.py
torch_mpo/models/vgg_mpo.py
torch_mpo/utils/__init__.py
torch_mpo/utils/compression.py
torch_mpo-0.2.1.dist-info/METADATA
torch_mpo-0.2.1.dist-info/WHEEL
torch_mpo-0.2.1.dist-info/licenses/LICENSE-APACHE
torch_mpo-0.2.1.dist-info/licenses/LICENSE-MIT
torch_mpo-0.2.1.dist-info/RECORD
