Metadata-Version: 2.4
Name: torch-mpo
Version: 0.2.1
Summary: PyTorch implementation of Matrix Product Operators for neural network compression
Project-URL: Homepage, https://github.com/krzysztofwos/torch-mpo
Project-URL: Repository, https://github.com/krzysztofwos/torch-mpo
Project-URL: Issues, https://github.com/krzysztofwos/torch-mpo/issues
Project-URL: Documentation, https://github.com/krzysztofwos/torch-mpo/blob/main/docs/tutorial.md
Author: Krzysztof Woś
Maintainer: Krzysztof Woś
License: MIT OR Apache-2.0
License-File: LICENSE-APACHE
License-File: LICENSE-MIT
Keywords: deep-learning,model-compression,mpo,neural-networks,pytorch,tensor-decomposition,tensor-train
Classifier: Development Status :: 4 - Beta
Classifier: Intended Audience :: Science/Research
Classifier: License :: OSI Approved :: Apache Software License
Classifier: License :: OSI Approved :: MIT License
Classifier: Programming Language :: Python :: 3
Classifier: Programming Language :: Python :: 3.12
Classifier: Topic :: Scientific/Engineering :: Artificial Intelligence
Requires-Python: >=3.12
Requires-Dist: matplotlib>=3.7.0
Requires-Dist: numpy>=1.24.0
Requires-Dist: pytorch-lightning>=2.0.0
Requires-Dist: tensorboard>=2.13.0
Requires-Dist: torch>=2.0.0
Requires-Dist: torchvision>=0.15.0
Requires-Dist: tqdm>=4.65.0
Requires-Dist: wandb>=0.15.0
Provides-Extra: dev
Requires-Dist: black>=23.3.0; extra == 'dev'
Requires-Dist: flake8>=6.0.0; extra == 'dev'
Requires-Dist: isort>=5.12.0; extra == 'dev'
Requires-Dist: mypy>=1.15.0; extra == 'dev'
Requires-Dist: pytest-asyncio>=0.26.0; extra == 'dev'
Requires-Dist: pytest-cov>=4.1.0; extra == 'dev'
Requires-Dist: pytest-mock>=3.14.0; extra == 'dev'
Requires-Dist: pytest>=8.3.5; extra == 'dev'
Provides-Extra: docs
Requires-Dist: sphinx-autodoc-typehints>=1.23.0; extra == 'docs'
Requires-Dist: sphinx-rtd-theme>=1.2.0; extra == 'docs'
Requires-Dist: sphinx>=6.2.0; extra == 'docs'
